vvnotebooks/__init__.py
vvnotebooks/snowflake/__init__.py
vvnotebooks-0.8.3.dist-info/LICENSE
vvnotebooks-0.8.3.dist-info/WHEEL
vvnotebooks-0.8.3.dist-info/METADATA
vvnotebooks-0.8.3.dist-info/RECORD
